menage_jupyter/__init__.py
menage_jupyter/clean.py
menage_jupyter/code.py
menage_jupyter/constans.py
menage_jupyter-0.1.3.dist-info/LICENSE.md
menage_jupyter-0.1.3.dist-info/WHEEL
menage_jupyter-0.1.3.dist-info/METADATA
menage_jupyter-0.1.3.dist-info/RECORD
