Metadata-Version: 2.1
Name: menage-jupyter
Version: 0.1.3
Summary: Simple package to menage jupyter files
License: CC BY
Author: Bartłomiej Chwiłkowski
Author-email: bartekchwilkowski@gmail.com
Requires-Python: >=3.8,<4.0
Classifier: License :: Other/Proprietary License
Classifier: Programming Language :: Python :: 3
Classifier: Programming Language :: Python :: 3.10
Classifier: Programming Language :: Python :: 3.8
Classifier: Programming Language :: Python :: 3.9
